CHANGES.rst
CONTRIBUTORS.rst
LATEST
MANIFEST.in
README.rst
requirements.txt
setup.cfg
setup.py
docs/LICENSE.GPL
docs/LICENSE.rst
docs/index.rst
scripts/proto2diazo.py
src/quaive/__init__.py
src/quaive.resources.ploneintranet.egg-info/PKG-INFO
src/quaive.resources.ploneintranet.egg-info/SOURCES.txt
src/quaive.resources.ploneintranet.egg-info/dependency_links.txt
src/quaive.resources.ploneintranet.egg-info/entry_points.txt
src/quaive.resources.ploneintranet.egg-info/namespace_packages.txt
src/quaive.resources.ploneintranet.egg-info/not-zip-safe
src/quaive.resources.ploneintranet.egg-info/requires.txt
src/quaive.resources.ploneintranet.egg-info/top_level.txt
src/quaive/resources/__init__.py
src/quaive/resources/ploneintranet/__init__.py
src/quaive/resources/ploneintranet/configure.zcml
src/quaive/resources/ploneintranet/interfaces.py
src/quaive/resources/ploneintranet/setuphandlers.py
src/quaive/resources/ploneintranet/testing.py
src/quaive/resources/ploneintranet/browser/__init__.py
src/quaive/resources/ploneintranet/browser/configure.zcml
src/quaive/resources/ploneintranet/browser/main_template.py
src/quaive/resources/ploneintranet/browser/templates/main_template.pt
src/quaive/resources/ploneintranet/profiles/default/browserlayer.xml
src/quaive/resources/ploneintranet/profiles/default/metadata.xml
src/quaive/resources/ploneintranet/profiles/default/registry.xml
src/quaive/resources/ploneintranet/profiles/default/theme.xml
src/quaive/resources/ploneintranet/profiles/uninstall/browserlayer.xml
src/quaive/resources/ploneintranet/profiles/uninstall/registry.xml
src/quaive/resources/ploneintranet/profiles/uninstall/theme.xml
src/quaive/resources/ploneintranet/static/README.md
src/quaive/resources/ploneintranet/static/manifest.cfg
src/quaive/resources/ploneintranet/static/preview.png
src/quaive/resources/ploneintranet/static/rules.xml
src/quaive/resources/ploneintranet/static/generated/404.html
src/quaive/resources/ploneintranet/static/generated/empty-home.html
src/quaive/resources/ploneintranet/static/generated/empty-workspace.html
src/quaive/resources/ploneintranet/static/generated/empty.html
src/quaive/resources/ploneintranet/static/generated/index.html
src/quaive/resources/ploneintranet/static/generated/library.html
src/quaive/resources/ploneintranet/static/generated/liz-baker.html
src/quaive/resources/ploneintranet/static/generated/news.html
src/quaive/resources/ploneintranet/static/generated/notifications.html
