Metadata-Version: 1.1
Name: quaive.resources.ploneintranet
Version: 2.0.8
Summary: Default theme for Plone Intranet
Home-page: https://github.com/quaive/quaive.resources.ploneintranet
Author: Quaive
Author-email: hello@quaive.com
License: GPL version 2
Keywords: Python Plone Quaive
Platform: UNKNOWN
Classifier: Environment :: Web Environment
Classifier: Framework :: Plone
Classifier: Framework :: Plone :: 5.0
Classifier: Programming Language :: Python
Classifier: Programming Language :: Python :: 2.7
Classifier: Operating System :: OS Independent
Classifier: License :: OSI Approved :: GNU General Public License v2 (GPLv2)
